LICENSE
MANIFEST.in
README.rst
setup.py
nose_timer.egg-info/PKG-INFO
nose_timer.egg-info/SOURCES.txt
nose_timer.egg-info/dependency_links.txt
nose_timer.egg-info/entry_points.txt
nose_timer.egg-info/pbr.json
nose_timer.egg-info/requires.txt
nose_timer.egg-info/top_level.txt
nosetimer/__init__.py
nosetimer/plugin.py