Metadata-Version: 1.1
Name: nose-timer
Version: 0.5.0
Summary: A timer plugin for nosetests
Home-page: https://github.com/mahmoudimus/nose-timer
Author: Juan Pedro Fisanotti, Mahmoud Abdelkader, Andres Riancho, Ivan Kolodyazhny, Kevin Burke, Anton Egorov, Dmitry Sandalov, Stanislav Kudriashev, Raoul Snyman, Corey Goldberg
Author-email: UNKNOWN
License: MIT or BSD
Platform: UNKNOWN
Classifier: Intended Audience :: Developers
Classifier: License :: OSI Approved :: MIT License
Classifier: License :: OSI Approved :: BSD License
Classifier: Natural Language :: English
Classifier: Operating System :: OS Independent
Classifier: Programming Language :: Python
Classifier: Programming Language :: Python :: 2
Classifier: Programming Language :: Python :: 2.6
Classifier: Programming Language :: Python :: 2.7
Classifier: Programming Language :: Python :: 3
Classifier: Programming Language :: Python :: 3.2
Classifier: Programming Language :: Python :: 3.3
Classifier: Programming Language :: Python :: 3.4
Classifier: Programming Language :: Python :: Implementation :: CPython
Classifier: Programming Language :: Python :: Implementation :: PyPy
Classifier: Topic :: Software Development :: Testing
Classifier: Environment :: Console
